{
    "page": 36,
    "label": "plain_text",
    "confidence": 0.5390610098838806,
    "bbox": [
        440.56939697265625,
        508.2879638671875,
        2111.376220703125,
        812.2176513671875
    ],
    "image_path": "debug/full_book/layout/page_036/006_plain_text_0.54.png",
    "text": "(b)What number would\ncontain the millionth digit?\nAns: The millionth digit\nin the\n occurs\nnumber\n185184+1=1,85,185.\n(c) When would\nyou have written\nthe digit \u201c5' for the 5000th time?\nAns: 13995"
}